Spring2026/LogicDesignComputerOrg/Labs/xaj3_eecs281_lab8/tbird_fsm.sv
typedef enum logic [2:0] {
  IDLE = 3'b000,
  L1   = 3'b001,
  L2   = 3'b011,
  L3   = 3'b010,
  R1   = 3'b101,
  R2   = 3'b111,
  R3   = 3'b110,
  LR3  = 3'b100
} t_tbird_lights_state;

module tbird_fsm (
    input  logic       clk,
    input  logic       rst_b,
    input  logic       left,
    input  logic       right,
    input  logic       haz,
    output logic [2:0] l_lights,
    output logic [2:0] r_lights
);
  t_tbird_lights_state state;

  always_ff @(posedge clk or negedge rst_b) begin
    if (~rst_b) state <= IDLE;
    else
      case (state)
        IDLE: begin
          if ((left & right) | haz) state <= LR3;
          else if (left) state <= L1;
          else if (right) state <= R1;
          else state <= IDLE;
        end
        L1:  state <= t_tbird_lights_state'(haz ? LR3 : L2);
        L2:  state <= t_tbird_lights_state'(haz ? LR3 : L3);
        L3:  state <= IDLE;
        R1:  state <= t_tbird_lights_state'(haz ? LR3 : R2);
        R2:  state <= t_tbird_lights_state'(haz ? LR3 : R3);
        R3:  state <= IDLE;
        LR3: state <= IDLE;
      endcase
  end

  always_comb begin
    case (state)
      IDLE: begin
        l_lights = 3'b000;
        r_lights = 3'b000;
      end
      L1: begin
        l_lights = 3'b001;
        r_lights = 3'b000;
      end
      L2: begin
        l_lights = 3'b011;
        r_lights = 3'b000;
      end
      L3: begin
        l_lights = 3'b111;
        r_lights = 3'b000;
      end
      R1: begin
        l_lights = 3'b000;
        r_lights = 3'b001;
      end
      R2: begin
        l_lights = 3'b000;
        r_lights = 3'b011;
      end
      R3: begin
        l_lights = 3'b000;
        r_lights = 3'b111;
      end
      LR3: begin
        l_lights = 3'b111;
        r_lights = 3'b111;
      end
    endcase
  end

endmodule

Spring2026/LogicDesignComputerOrg/Labs/xaj3_eecs281_lab8/testbench_hw8.sv
module testbench_hw8 ();

  logic clk, rst_b, left, right, haz;
  logic [2:0] l_lights, r_lights;

  tbird_fsm UUT (
      .clk(clk),
      .rst_b(rst_b),
      .left(left),
      .right(right),
      .haz(haz),
      .l_lights(l_lights),
      .r_lights(r_lights)
  );

  initial begin
    clk   = 1'b0;
    rst_b = 1'b1;
    left  = 1'b0;
    right = 1'b0;
    haz   = 1'b0;

    forever #5 clk = ~clk;
  end

  initial begin
    #10;
    rst_b = 1'b0;
    #20;
    rst_b = 1'b1;
    #20;
    right = 1'b1;
    #40;
    right = 1'b0;
    left  = 1'b1;
    #40;
    left  = 1'b0;
    right = 1'b1;
    #10;
    right = 1'b0;
    haz   = 1'b1;
    #10;
    haz = 1'b0;
    #10;
    right = 1'b1;
    #20;
    right = 1'b0;
    haz   = 1'b1;
    #10;
    haz = 1'b0;
    #10;
    left = 1'b1;
    #10;
    left = 1'b0;
    haz  = 1'b1;
    #10;
    haz = 1'b0;
    #10;
    left = 1'b1;
    #20;
    left = 1'b0;
    haz  = 1'b1;
    #10;
    haz = 1'b0;
    #10;
    $finish();
  end

  initial begin
    $dumpfile("dump.vcd");
    $dumpvars(0, testbench_hw8);

    $display("rst_b | Left | Right | Haz | L_Lights | R_Lights");
    $monitor("%1b     | %1b    | %1b     | %1b   |   %3b    |   %3b   ", rst_b, left, right, haz,
             l_lights, r_lights);

    #280;
  end
endmodule

Spring2026/LogicDesignComputerOrg/Labs/xaj3_eecs281_lab8/dump.vcd
$date
	Thu Apr  9 11:02:02 2026
$end
$version
	Icarus Verilog
$end
$timescale
	1s
$end
$scope module testbench_hw8 $end
$var wire 3 ! r_lights [2:0] $end
$var wire 3 " l_lights [2:0] $end
$var reg 1 # clk $end
$var reg 1 $ haz $end
$var reg 1 % left $end
$var reg 1 & right $end
$var reg 1 ' rst_b $end
$scope module UUT $end
$var wire 1 # clk $end
$var wire 1 $ haz $end
$var wire 1 % left $end
$var wire 1 & right $end
$var wire 1 ' rst_b $end
$var reg 3 ( l_lights [2:0] $end
$var reg 3 ) r_lights [2:0] $end
$var reg 3 * state [2:0] $end
$upscope $end
$upscope $end
$enddefinitions $end
$comment Show the parameter values. $end
$dumpall
$end
#0
$dumpvars
bx *
bx )
bx (
1'
0&
0%
0$
0#
bx "
bx !
$end
#5
1#
#10
b0 !
b0 )
b0 "
b0 (
b0 *
0#
0'
#15
1#
#20
0#
#25
1#
#30
0#
1'
#35
1#
#40
0#
#45
1#
#50
0#
1&
#55
b1 !
b1 )
b101 *
1#
#60
0#
#65
b11 !
b11 )
b111 *
1#
#70
0#
#75
b111 !
b111 )
b110 *
1#
#80
0#
#85
b0 !
b0 )
b0 *
1#
#90
0#
1%
0&
#95
b1 "
b1 (
b1 *
1#
#100
0#
#105
b11 "
b11 (
b11 *
1#
#110
0#
#115
b111 "
b111 (
b10 *
1#
#120
0#
#125
b0 "
b0 (
b0 *
1#
#130
0#
1&
0%
#135
b1 !
b1 )
b101 *
1#
#140
0#
1$
0&
#145
b111 !
b111 )
b111 "
b111 (
b100 *
1#
#150
0#
0$
#155
b0 !
b0 )
b0 "
b0 (
b0 *
1#
#160
0#
1&
#165
b1 !
b1 )
b101 *
1#
#170
0#
#175
b11 !
b11 )
b111 *
1#
#180
0#
1$
0&
#185
b111 !
b111 )
b111 "
b111 (
b100 *
1#
#190
0#
0$
#195
b0 !
b0 )
b0 "
b0 (
b0 *
1#
#200
0#
1%
#205
b1 "
b1 (
b1 *
1#
#210
0#
1$
0%
#215
b111 !
b111 )
b111 "
b111 (
b100 *
1#
#220
0#
0$
#225
b0 !
b0 )
b0 "
b0 (
b0 *
1#
#230
0#
1%
#235
b1 "
b1 (
b1 *
1#
#240
0#
#245
b11 "
b11 (
b11 *
1#
#250
0#
1$
0%
#255
b111 !
b111 )
b111 "
b111 (
b100 *
1#
#260
0#
0$
#265
b0 !
b0 )
b0 "
b0 (
b0 *
1#
