Spring2026/LogicDesignComputerOrg/Labs/xaj3_eecs281_lab7/up_down_counter.sv
module up_down_counter #(
    parameter N = 4
) (
    input  logic         clk,
    input  logic         en_b,
    input  logic         load_b,
    input  logic         up,
    input  logic [N-1:0] load_in,
    output logic [N-1:0] q,
    output logic         rco_b
);
  always_ff @(posedge clk) begin
    if (~en_b) begin
      if (load_b) begin
        q <= up ? q++ : q--;
      end else begin
        q <= load_in;
      end
    end
  end

  assign rco_b = up ? q == '1 : q == '0;

endmodule

Spring2026/LogicDesignComputerOrg/Labs/xaj3_eecs281_lab7/testbench_hw7.sv
module testbench_hw7 ();
  logic clk, en_b;
  logic up;

  logic load4_b;
  logic [3:0] load_in4;
  logic [3:0] q4;
  logic rco4_b;

  logic load5_b;
  logic [4:0] load_in5;
  logic [4:0] q5;
  logic rco5_b;


  up_down_counter #(
      .N(4)
  ) counter4 (
      .clk    (clk),
      .en_b   (en_b),
      .load_b (load4_b),
      .up     (up),
      .load_in(load_in4),
      .q      (q4),
      .rco_b  (rco4_b)
  );

  up_down_counter #(
      .N(5)
  ) counter5 (
      .clk    (clk),
      .en_b   (en_b),
      .load_b (load5_b),
      .up     (up),
      .load_in(load_in5),
      .q      (q5),
      .rco_b  (rco5_b)
  );

  initial begin
    clk      = 1'b0;
    en_b     = 1'b1;
    load4_b  = 1'b0;
    load5_b  = 1'b0;
    up       = 1'b1;
    load_in4 = 4'b0000;
    load_in5 = 5'b00000;

    forever #5 clk = ~clk;
  end

  initial begin

    #10;
    load4_b = 1'b0;
    load5_b = 1'b0;
    #10;
    en_b = 1'b0;
    #10;
    load4_b = 1'b1;
    load5_b = 1'b1;
    #320;
    en_b     = 1'b1;
    up       = 1'b0;
    load4_b  = 1'b0;
    load5_b  = 1'b0;
    load_in4 = 4'b1111;
    load_in5 = 5'b11111;
    #10;
    en_b = 1'b0;
    #10;
    load4_b = 1'b1;
    load5_b = 1'b1;
    en_b    = 1'b1;
    #10;
    en_b = 1'b0;
    #320;
    load4_b  = 1'b0;
    load5_b  = 1'b0;
    load_in4 = 4'b1010;
    load_in5 = 5'b01010;
    #10;
    load4_b = 1'b1;
    load5_b = 1'b1;
    #10;
    up       = 1'b1;
    load4_b  = 1'b0;
    load5_b  = 1'b0;
    load_in4 = 4'b0101;
    load_in5 = 5'b10101;
    #10;
    load4_b = 1'b1;
    load5_b = 1'b1;
    #14;
    $finish();
  end

  initial begin
    $dumpfile("dump.vcd");
    $dumpvars(0, testbench_hw7);

    $display(
        "CLOCK | Enable | Up |  Q4  | Load Bit: 4 | Load Input: 4 | RCO 4 |   Q5   | Load Bit: 5 | Load Input: 5 | RCO 5");
    $monitor(
        " %1b    | %1b      | %1b  | %4b |    %4b     |     %4b      | %4b  | %5b  |    %5b    |     %5b     | %5b   ",
        clk, en_b, up, q4, load4_b, load_in4, rco4_b, q5, load5_b, load_in5, rco5_b);

    #744;
    $finish();
  end

endmodule

Spring2026/LogicDesignComputerOrg/Labs/xaj3_eecs281_lab7/dump.vcd
$date
	Wed Apr  1 16:04:31 2026
$end
$version
	Icarus Verilog
$end
$timescale
	100ps
$end
$scope module testbench_hw7 $end
$var wire 1 ! rco5_b $end
$var wire 1 " rco4_b $end
$var wire 5 # q5 [4:0] $end
$var wire 4 $ q4 [3:0] $end
$var reg 1 % clk $end
$var reg 1 & en_b $end
$var reg 1 ' load4_b $end
$var reg 1 ( load5_b $end
$var reg 4 ) load_in4 [3:0] $end
$var reg 5 * load_in5 [4:0] $end
$var reg 1 + up $end
$scope module counter4 $end
$var wire 1 % clk $end
$var wire 1 & en_b $end
$var wire 1 ' load_b $end
$var wire 4 , load_in [3:0] $end
$var wire 1 + up $end
$var wire 1 " rco_b $end
$var parameter 32 - N $end
$var reg 4 . q [3:0] $end
$upscope $end
$scope module counter5 $end
$var wire 1 % clk $end
$var wire 1 & en_b $end
$var wire 1 ( load_b $end
$var wire 5 / load_in [4:0] $end
$var wire 1 + up $end
$var wire 1 ! rco_b $end
$var parameter 32 0 N $end
$var reg 5 1 q [4:0] $end
$upscope $end
$upscope $end
$enddefinitions $end
$comment Show the parameter values. $end
$dumpall
b101 0
b100 -
$end
#0
$dumpvars
bx 1
b0 /
bx .
b0 ,
1+
b0 *
b0 )
0(
0'
1&
0%
bx $
bx #
x"
x!
$end
#50
1%
#100
0%
#150
1%
#200
0%
0&
#250
0"
0!
b0 $
b0 .
b0 #
b0 1
1%
#300
0%
1(
1'
#350
b0 #
b0 1
b0 $
b0 .
1%
#400
0%
#450
b0 $
b0 .
b0 #
b0 1
1%
#500
0%
#550
b0 #
b0 1
b0 $
b0 .
1%
#600
0%
#650
b0 $
b0 .
b0 #
b0 1
1%
#700
0%
#750
b0 #
b0 1
b0 $
b0 .
1%
#800
0%
#850
b0 $
b0 .
b0 #
b0 1
1%
#900
0%
#950
b0 #
b0 1
b0 $
b0 .
1%
#1000
0%
#1050
b0 $
b0 .
b0 #
b0 1
1%
#1100
0%
#1150
b0 #
b0 1
b0 $
b0 .
1%
#1200
0%
#1250
b0 $
b0 .
b0 #
b0 1
1%
#1300
0%
#1350
b0 #
b0 1
b0 $
b0 .
1%
#1400
0%
#1450
b0 $
b0 .
b0 #
b0 1
1%
#1500
0%
#1550
b0 #
b0 1
b0 $
b0 .
1%
#1600
0%
#1650
b0 $
b0 .
b0 #
b0 1
1%
#1700
0%
#1750
b0 #
b0 1
b0 $
b0 .
1%
#1800
0%
#1850
b0 $
b0 .
b0 #
b0 1
1%
#1900
0%
#1950
b0 #
b0 1
b0 $
b0 .
1%
#2000
0%
#2050
b0 $
b0 .
b0 #
b0 1
1%
#2100
0%
#2150
b0 #
b0 1
b0 $
b0 .
1%
#2200
0%
#2250
b0 $
b0 .
b0 #
b0 1
1%
#2300
0%
#2350
b0 #
b0 1
b0 $
b0 .
1%
#2400
0%
#2450
b0 $
b0 .
b0 #
b0 1
1%
#2500
0%
#2550
b0 #
b0 1
b0 $
b0 .
1%
#2600
0%
#2650
b0 $
b0 .
b0 #
b0 1
1%
#2700
0%
#2750
b0 #
b0 1
b0 $
b0 .
1%
#2800
0%
#2850
b0 $
b0 .
b0 #
b0 1
1%
#2900
0%
#2950
b0 #
b0 1
b0 $
b0 .
1%
#3000
0%
#3050
b0 $
b0 .
b0 #
b0 1
1%
#3100
0%
#3150
b0 #
b0 1
b0 $
b0 .
1%
#3200
0%
#3250
b0 $
b0 .
b0 #
b0 1
1%
#3300
0%
#3350
b0 #
b0 1
b0 $
b0 .
1%
#3400
0%
#3450
b0 $
b0 .
b0 #
b0 1
1%
#3500
1"
1!
0%
b11111 *
b11111 /
b1111 )
b1111 ,
0(
0'
0+
1&
#3550
1%
#3600
0%
0&
#3650
0"
0!
b1111 $
b1111 .
b11111 #
b11111 1
1%
#3700
0%
1&
1(
1'
#3750
1%
#3800
0%
0&
#3850
b1111 $
b1111 .
b11111 #
b11111 1
1%
#3900
0%
#3950
b11111 #
b11111 1
b1111 $
b1111 .
1%
#4000
0%
#4050
b1111 $
b1111 .
b11111 #
b11111 1
1%
#4100
0%
#4150
b11111 #
b11111 1
b1111 $
b1111 .
1%
#4200
0%
#4250
b1111 $
b1111 .
b11111 #
b11111 1
1%
#4300
0%
#4350
b11111 #
b11111 1
b1111 $
b1111 .
1%
#4400
0%
#4450
b1111 $
b1111 .
b11111 #
b11111 1
1%
#4500
0%
#4550
b11111 #
b11111 1
b1111 $
b1111 .
1%
#4600
0%
#4650
b1111 $
b1111 .
b11111 #
b11111 1
1%
#4700
0%
#4750
b11111 #
b11111 1
b1111 $
b1111 .
1%
#4800
0%
#4850
b1111 $
b1111 .
b11111 #
b11111 1
1%
#4900
0%
#4950
b11111 #
b11111 1
b1111 $
b1111 .
1%
#5000
0%
#5050
b1111 $
b1111 .
b11111 #
b11111 1
1%
#5100
0%
#5150
b11111 #
b11111 1
b1111 $
b1111 .
1%
#5200
0%
#5250
b1111 $
b1111 .
b11111 #
b11111 1
1%
#5300
0%
#5350
b11111 #
b11111 1
b1111 $
b1111 .
1%
#5400
0%
#5450
b1111 $
b1111 .
b11111 #
b11111 1
1%
#5500
0%
#5550
b11111 #
b11111 1
b1111 $
b1111 .
1%
#5600
0%
#5650
b1111 $
b1111 .
b11111 #
b11111 1
1%
#5700
0%
#5750
b11111 #
b11111 1
b1111 $
b1111 .
1%
#5800
0%
#5850
b1111 $
b1111 .
b11111 #
b11111 1
1%
#5900
0%
#5950
b11111 #
b11111 1
b1111 $
b1111 .
1%
#6000
0%
#6050
b1111 $
b1111 .
b11111 #
b11111 1
1%
#6100
0%
#6150
b11111 #
b11111 1
b1111 $
b1111 .
1%
#6200
0%
#6250
b1111 $
b1111 .
b11111 #
b11111 1
1%
#6300
0%
#6350
b11111 #
b11111 1
b1111 $
b1111 .
1%
#6400
0%
#6450
b1111 $
b1111 .
b11111 #
b11111 1
1%
#6500
0%
#6550
b11111 #
b11111 1
b1111 $
b1111 .
1%
#6600
0%
#6650
b1111 $
b1111 .
b11111 #
b11111 1
1%
#6700
0%
#6750
b11111 #
b11111 1
b1111 $
b1111 .
1%
#6800
0%
#6850
b1111 $
b1111 .
b11111 #
b11111 1
1%
#6900
0%
#6950
b11111 #
b11111 1
b1111 $
b1111 .
1%
#7000
0%
b1010 *
b1010 /
b1010 )
b1010 ,
0(
0'
#7050
b1010 $
b1010 .
b1010 #
b1010 1
1%
#7100
0%
1(
1'
#7150
b1010 #
b1010 1
b1010 $
b1010 .
1%
#7200
0%
b10101 *
b10101 /
b101 )
b101 ,
0(
0'
1+
#7250
b101 $
b101 .
b10101 #
b10101 1
1%
#7300
0%
1(
1'
#7350
b10101 #
b10101 1
b101 $
b101 .
1%
