Spring2026/LogicDesignComputerOrg/Labs/xaj3_eecs281_lab6/lab6.sv
module lab6 ();

  function logic [7:0] decoder3to8(logic en_b, logic [2:0] in);
    casex ({
      en_b, in
    })
      4'b1xxx: return 8'b1111_1111;
      4'b0000: return 8'b1111_1110;
      4'b0001: return 8'b1111_1101;
      4'b0010: return 8'b1111_1011;
      4'b0011: return 8'b1111_0111;
      4'b0100: return 8'b1110_1111;
      4'b0101: return 8'b1101_1111;
      4'b0110: return 8'b1011_1111;
      4'b0111: return 8'b0111_1111;
      default: return 8'b1111_1111;
    endcase
  endfunction

  function logic [2:0] encoder8to3(logic en_b, logic [7:0] in_b);
    casex ({
      en_b, in_b
    })
      9'b1_xxxxxxxx: return 3'b111;
      9'b0_0xxxxxxx: return 3'b111;
      9'b0_10xxxxxx: return 3'b110;
      9'b0_110xxxxx: return 3'b101;
      9'b0_1110xxxx: return 3'b100;
      9'b0_11110xxx: return 3'b011;
      9'b0_111110xx: return 3'b010;
      9'b0_1111110x: return 3'b001;
      9'b0_11111110: return 3'b000;
      default: return 3'b000;
    endcase
  endfunction

  logic [2:0] in, out;
  logic [7:0] d_out;
  logic clk;

  always_comb begin
    d_out = decoder3to8(~clk, in);
    out   = encoder8to3(~clk, d_out);
  end

  initial begin
    clk = 1'b1;
    in  = 3'b111;
    forever #5 clk = ~clk;
  end

  always @(posedge clk) in += 1;


  initial begin
    $dumpfile("dump.vcd");
    $dumpvars(0, lab6);

    $display("CLOCK |  IN  |  Decoder OUT  |  Encoder OUT  ");
    $monitor("   %1b  | %3b |   %8b    |      %3b      ", clk, in, d_out, out);

    #82 $finish();
  end

endmodule

Spring2026/LogicDesignComputerOrg/Labs/xaj3_eecs281_lab6/dump.vcd
$date
	Wed Mar 18 10:23:34 2026
$end
$version
	Icarus Verilog
$end
$timescale
	1s
$end
$scope module lab6 $end
$var reg 1 ! clk $end
$var reg 8 " d_out [7:0] $end
$var reg 3 # in [2:0] $end
$var reg 3 $ out [2:0] $end
$scope function decoder3to8 $end
$var reg 1 % en_b $end
$var reg 3 & in [2:0] $end
$upscope $end
$scope function encoder8to3 $end
$var reg 1 ' en_b $end
$var reg 8 ( in_b [7:0] $end
$upscope $end
$upscope $end
$enddefinitions $end
$comment Show the parameter values. $end
$dumpall
$end
#0
$dumpvars
b1111111 (
0'
b111 &
0%
b111 $
b111 #
b1111111 "
1!
$end
#5
1'
b11111111 (
b11111111 "
1%
0!
#10
b0 $
b0 &
b0 #
0'
b11111110 (
b11111110 "
0%
1!
#15
b111 $
1'
b11111111 (
b11111111 "
1%
0!
#20
b1 &
b1 #
b1 $
0'
b11111101 (
b11111101 "
0%
1!
#25
b111 $
1'
b11111111 (
b11111111 "
1%
0!
#30
b10 &
b10 #
b10 $
0'
b11111011 (
b11111011 "
0%
1!
#35
b111 $
1'
b11111111 (
b11111111 "
1%
0!
#40
b11 &
b11 #
b11 $
0'
b11110111 (
b11110111 "
0%
1!
#45
b111 $
1'
b11111111 (
b11111111 "
1%
0!
#50
b100 &
b100 #
b100 $
0'
b11101111 (
b11101111 "
0%
1!
#55
b111 $
1'
b11111111 (
b11111111 "
1%
0!
#60
b101 &
b101 #
b101 $
0'
b11011111 (
b11011111 "
0%
1!
#65
b111 $
1'
b11111111 (
b11111111 "
1%
0!
#70
b110 &
b110 #
b110 $
0'
b10111111 (
b10111111 "
0%
1!
#75
b111 $
1'
b11111111 (
b11111111 "
1%
0!
#80
b111 &
b111 #
b111 $
0'
b1111111 (
b1111111 "
0%
1!
